jlab_archiver_client/__init__.py
jlab_archiver_client/channel.py
jlab_archiver_client/config.py
jlab_archiver_client/exceptions.py
jlab_archiver_client/interval.py
jlab_archiver_client/mysampler.py
jlab_archiver_client/mystats.py
jlab_archiver_client/point.py
jlab_archiver_client/query.py
jlab_archiver_client/scripts.py
jlab_archiver_client/utils.py
jlab_archiver_client-2.0.1.dist-info/METADATA
jlab_archiver_client-2.0.1.dist-info/WHEEL
jlab_archiver_client-2.0.1.dist-info/entry_points.txt
jlab_archiver_client-2.0.1.dist-info/top_level.txt
jlab_archiver_client-2.0.1.dist-info/RECORD
