Metadata-Version: 2.4
Name: jlab_archiver_client
Version: 2.0.1
Summary: Software library for interacting with myquery web service
Author-email: Adam Carpenter <adamc@jlab.org>
License: JLab
Keywords: mya,MYA,myquery
Classifier: Programming Language :: Python :: 3
Requires-Python: >=3.11
Requires-Dist: numpy<3.0,>=2.0.0
Requires-Dist: pandas<3.0,>=2.2.2
Requires-Dist: requests<3,>=2.28.2
Provides-Extra: dev
Requires-Dist: pytest<9.0,>=8.3; extra == "dev"
Requires-Dist: pytest-cov<7.0,>=6.0.0; extra == "dev"
Requires-Dist: build<2.0,>=1.2; extra == "dev"
Requires-Dist: Sphinx<9.0,>=8.1; extra == "dev"
Requires-Dist: sphinx-autodoc-typehints<4.0,>=3.0; extra == "dev"
Requires-Dist: sphinx-rtd-theme<4.0,>=3.0; extra == "dev"
Requires-Dist: myst-parser<5.0,>=4.0.1; extra == "dev"
Requires-Dist: ruff<1.0,>=0.8.0; extra == "dev"
